dead_simple_telegram/__init__.py
dead_simple_telegram/client.py
dead_simple_telegram-0.1.3.dist-info/licenses/LICENSE
dead_simple_telegram-0.1.3.dist-info/METADATA
dead_simple_telegram-0.1.3.dist-info/WHEEL
dead_simple_telegram-0.1.3.dist-info/top_level.txt
dead_simple_telegram-0.1.3.dist-info/RECORD
