Metadata-Version: 2.4
Name: dead-simple-telegram
Version: 0.1.3
Summary: Dead simple helper for posting Telegram bot messages.
Home-page: https://github.com/rioncm/simple-telegram
Author: Rion Morgenstern
License: MIT
Project-URL: Homepage, https://github.com/rioncm/simple-telegram
Project-URL: Repository, https://github.com/rioncm/simple-telegram
Project-URL: Issues, https://github.com/rioncm/simple-telegram/issues
Keywords: telegram,bot,notification
Classifier: Development Status :: 3 - Alpha
Classifier: Intended Audience :: Developers
Classifier: License :: OSI Approved :: MIT License
Classifier: Programming Language :: Python :: 3
Classifier: Programming Language :: Python :: 3 :: Only
Classifier: Programming Language :: Python :: 3.9
Classifier: Programming Language :: Python :: 3.10
Classifier: Programming Language :: Python :: 3.11
Classifier: Programming Language :: Python :: 3.12
Classifier: Programming Language :: Python :: 3.13
Classifier: Topic :: Communications :: Chat
Requires-Python: >=3.9
License-File: LICENSE
Requires-Dist: requests>=2.0
Provides-Extra: dev
Requires-Dist: pytest>=7; extra == "dev"
Dynamic: license-file
